{
  "工作内容概述_description": "岗位主要涉及线上销售、客户开发、数据分析、直播电商运营及私域客户维护等工作。核心职责包括通过电商平台（如抖音、快手、小红书）进行商品推广和客户引流，开展直播互动并收集潜在客户信息，通过电话、微信等方式进行客户沟通与维护，分析直播及短视频平台的数据以优化营销策略，同时负责招商加盟、产品推广及销售目标达成。工作内容以销售和客户管理为主，需具备良好的沟通能力、数据分析能力和电商平台运营经验。",
  "工作内容概述_tags": [
    "直播电商运营",
    "私域客户维护",
    "精准流量获客",
    "电商平台推广",
    "数据分析统计",
    "招商加盟对接",
    "客户电话沟通",
    "短视频内容分析",
    "销售目标达成",
    "线上渠道开发"
  ],
  "工作内容概述_features": [
    {
      "feature_name": "直播电商运营",
      "confidence": "high",
      "frequency": 2,
      "evidence_count": 2,
      "sample_evidence": [
        "【工作内容】 直播电商+私域运营的模式，精准流量获客白酒爱好者，针对公司提供的精准客户，网络进行日常维护，介绍白酒文化及公司产品，从而进行再次复购！",
        "1、预热视频拍摄及定点直播，保证直播场次，2、形象好，气质佳，具备销售经验优先，有无经验均可。3、洞察思维能力强，语言表达能力逻辑清晰。"
      ]
    },
    {
      "feature_name": "私域客户维护",
      "confidence": "high",
      "frequency": 2,
      "evidence_count": 2,
      "sample_evidence": [
        "【工作内容】 直播电商+私域运营的模式，精准流量获客白酒爱好者，针对公司提供的精准客户，网络进行日常维护，介绍白酒文化及公司产品，从而进行再次复购！",
        "公司从事大健康行业，针对初次订购的顾客，电话回访加微信，给予指导和维护，促成复购。"
      ]
    },
    {
      "feature_name": "电商平台推广",
      "confidence": "medium",
      "frequency": 3,
      "evidence_count": 3,
      "sample_evidence": [
        "通过小红书，抖音，快手引流，背靠平台，负责发掘客户，促销，留存，可以做全品类项目，服装，食品，大健康，自由选择任职资格：有一定的私域资源，想往电商行业发展，自媒体博主优先，有无经验均可，初期有人带有人培训工资结算：",
        "五险一金、节日关怀礼、年假、婚假、产假等。【工作的具体内容】1、通过小红书、抖音、安居客、乐有家网等渠道，开发和维护房源/客源；",
        "该岗位的详细职责和要求（包含了该岗位对技术能力的要求）如下： 1、在电商平台通过关键词搜索，开发客户2、主要是1688找工厂赛道（搜索蕾丝服装厂）3、拼多多 淘宝天猫，小红书 抖音（搜索服装厂），TK等商家4、阿里国际站RFQ询盘，每天进行RFQ的客户背调与筛选客户社媒INS, TWITTER，Whatsapp 等开发事项 上班时间早上9："
      ]
    },
    {
      "feature_name": "数据分析统计",
      "confidence": "medium",
      "frequency": 2,
      "evidence_count": 2,
      "sample_evidence": [
        "2、数据分析：直播期间、短视频、小红书等其他媒体渠道的留资数据统计、分析；",
        "对各汽车网站保持至少每天发布厂家要求数量的软文;7、负责各网站的编辑，页面更新;8、(收集)周边同品牌的网上报价信息;9、收集全体留资信息并转交电话呼入、呼出专员;10、回复客户在线提出的全体疑问。"
      ]
    },
    {
      "feature_name": "招商加盟对接",
      "confidence": "medium",
      "frequency": 1,
      "evidence_count": 1,
      "sample_evidence": [
        "工作内容：集团主做消防工程，旗下7家子公司拥有工程类所有资质，主要工作内容是与全国中小型工程企业联系，面向全国招商加盟分公司，房屋检测类项目，消防设计图纸项目，谈好费用即可，后续有专员对接，一周内基本可以掌握业务话术，公司有推广专员做广告推广，提供业务数据。"
      ]
    },
    {
      "feature_name": "客户电话沟通",
      "confidence": "medium",
      "frequency": 1,
      "evidence_count": 1,
      "sample_evidence": [
        "公司从事大健康行业，针对初次订购的顾客，电话回访加微信，给予指导和维护，促成复购。"
      ]
    },
    {
      "feature_name": "短视频内容分析",
      "confidence": "low",
      "frequency": 1,
      "evidence_count": 1,
      "sample_evidence": [
        "分析平台爆品逻辑，且有目标的达人，5.与各达人排直播日期，跟踪产品的带货情况。"
      ]
    }
  ],
  "_metadata": {
    "total_raw_items": 66,
    "valid_features": 7,
    "filtered_noise_count": 27,
    "processing_notes": "原始数据中包含大量与岗位职责无关的噪声信息（如公司介绍、招聘流程等），已全部过滤。最终特征均基于有效原文提取，无编造内容。"
  }
}